{"lastUsed":1775699853501,"path":"\/home\/milton\/eclipse-workspace\/CursoAbril2026","projectCount":7,"recentFiles":[{"path":"\/Proyecto1Objeto\/src","parentWorkspace":"\/home\/milton\/eclipse-workspace\/CursoAbril2026","name":"Movie.java","lastModified":1775575339366,"locationURI":"file:\/home\/milton\/eclipse-workspace\/CursoAbril2026\/Proyecto1Objeto\/src\/Movie.java"},{"path":"\/Ejercicio4Banco\/src","parentWorkspace":"\/home\/milton\/eclipse-workspace\/CursoAbril2026","name":"Main.java","lastModified":1775699793077,"locationURI":"file:\/home\/milton\/eclipse-workspace\/CursoAbril2026\/Ejercicio4Banco\/src\/Main.java"},{"path":"\/Ejercicio2Autos\/src","parentWorkspace":"\/home\/milton\/eclipse-workspace\/CursoAbril2026","name":"Autos.java","lastModified":1775583205800,"locationURI":"file:\/home\/milton\/eclipse-workspace\/CursoAbril2026\/Ejercicio2Autos\/src\/Autos.java"},{"path":"\/Ejercicio1Peliculas\/src","parentWorkspace":"\/home\/milton\/eclipse-workspace\/CursoAbril2026","name":"Main.java","lastModified":1775583453960,"locationURI":"file:\/home\/milton\/eclipse-workspace\/CursoAbril2026\/Ejercicio1Peliculas\/src\/Main.java"},{"path":"\/Ejercicio3Productos\/src","parentWorkspace":"\/home\/milton\/eclipse-workspace\/CursoAbril2026","name":"Main.java","lastModified":1775678791084,"locationURI":"file:\/home\/milton\/eclipse-workspace\/CursoAbril2026\/Ejercicio3Productos\/src\/Main.java"},{"path":"\/Ejercicio3Productos\/src","parentWorkspace":"\/home\/milton\/eclipse-workspace\/CursoAbril2026","name":"Productos.java","lastModified":1775669107188,"locationURI":"file:\/home\/milton\/eclipse-workspace\/CursoAbril2026\/Ejercicio3Productos\/src\/Productos.java"},{"path":"\/Proyecto2ListasCD\/src","parentWorkspace":"\/home\/milton\/eclipse-workspace\/CursoAbril2026","name":"Empleados.java","lastModified":1775590394418,"locationURI":"file:\/home\/milton\/eclipse-workspace\/CursoAbril2026\/Proyecto2ListasCD\/src\/Empleados.java"},{"path":"\/Proyecto2ListasCD\/src","parentWorkspace":"\/home\/milton\/eclipse-workspace\/CursoAbril2026","name":"Main.java","lastModified":1775681609117,"locationURI":"file:\/home\/milton\/eclipse-workspace\/CursoAbril2026\/Proyecto2ListasCD\/src\/Main.java"},{"path":"\/Proyecto1Objeto\/src","parentWorkspace":"\/home\/milton\/eclipse-workspace\/CursoAbril2026","name":"Principal.java","lastModified":1775573736424,"locationURI":"file:\/home\/milton\/eclipse-workspace\/CursoAbril2026\/Proyecto1Objeto\/src\/Principal.java"},{"path":"\/Ejercicio4Banco\/src","parentWorkspace":"\/home\/milton\/eclipse-workspace\/CursoAbril2026","name":"Banco.java","lastModified":1775682636246,"locationURI":"file:\/home\/milton\/eclipse-workspace\/CursoAbril2026\/Ejercicio4Banco\/src\/Banco.java"},{"path":"\/Ejercicio1Peliculas\/src","parentWorkspace":"\/home\/milton\/eclipse-workspace\/CursoAbril2026","name":"Movie.java","lastModified":1775576865583,"locationURI":"file:\/home\/milton\/eclipse-workspace\/CursoAbril2026\/Ejercicio1Peliculas\/src\/Movie.java"},{"path":"\/Ejercicio3Celulares\/src","parentWorkspace":"\/home\/milton\/eclipse-workspace\/CursoAbril2026","name":"Main.java","lastModified":1775667613395,"locationURI":"file:\/home\/milton\/eclipse-workspace\/CursoAbril2026\/Ejercicio3Celulares\/src\/Main.java"},{"path":"\/Ejercicio2Autos\/src","parentWorkspace":"\/home\/milton\/eclipse-workspace\/CursoAbril2026","name":"Main.java","lastModified":1775590187131,"locationURI":"file:\/home\/milton\/eclipse-workspace\/CursoAbril2026\/Ejercicio2Autos\/src\/Main.java"},{"path":"\/Ejercicio3Celulares\/src","parentWorkspace":"\/home\/milton\/eclipse-workspace\/CursoAbril2026","name":"Celular.java","lastModified":1775592987515,"locationURI":"file:\/home\/milton\/eclipse-workspace\/CursoAbril2026\/Ejercicio3Celulares\/src\/Celular.java"},{"path":"\/Proyecto1Objeto\/src","parentWorkspace":"\/home\/milton\/eclipse-workspace\/CursoAbril2026","name":"Computadoras.java","lastModified":1775574157965,"locationURI":"file:\/home\/milton\/eclipse-workspace\/CursoAbril2026\/Proyecto1Objeto\/src\/Computadoras.java"}]}